firewall/__init__.py
firewall/cache.py
firewall/command.py
firewall/config.py
firewall/core.py
firewall/daemonutil.py
firewall/getifaddrs.py
firewall/main.py
firewall/mini_http.py
firewall/parser.py
firewall/service.py
firewall/traflog.py
firewall/util.py
firewall/modules/__init__.py
firewall/modules/filter.py
firewall/modules/iptables.py
firewall/modules/manual.py
firewall/modules/nat.py
firewall/modules/sshkill.py
firewall/modules/trafmon.py
ktpanda_firewall-1.0.2.data/scripts/firewall
ktpanda_firewall-1.0.2.data/scripts/fwctl
ktpanda_firewall-1.0.2.data/scripts/ssh_logmon_systemd
ktpanda_firewall-1.0.2.dist-info/LICENSE
ktpanda_firewall-1.0.2.dist-info/METADATA
ktpanda_firewall-1.0.2.dist-info/WHEEL
ktpanda_firewall-1.0.2.dist-info/top_level.txt
ktpanda_firewall-1.0.2.dist-info/RECORD
