Metadata-Version: 2.1
Name: ktpanda-firewall
Version: 1.0.2
Summary: A modular firewall manager
Home-page: https://ktpanda.org/software/ktpanda-firewall
Author: Katie Rust
Author-email: katie@ktpanda.org
License: MIT License
Classifier: Programming Language :: Python :: 3
Classifier: License :: OSI Approved :: MIT License
Classifier: Operating System :: OS Independent
Requires-Python: >=3.7
License-File: LICENSE
Requires-Dist: systemd-python (>=234)
